.gitignore
.travis.yml
README.rst
requirements.txt
setup.py
zerotk.lib.iml
zerotk/__init__.py
zerotk.lib.egg-info/PKG-INFO
zerotk.lib.egg-info/SOURCES.txt
zerotk.lib.egg-info/dependency_links.txt
zerotk.lib.egg-info/namespace_packages.txt
zerotk.lib.egg-info/requires.txt
zerotk.lib.egg-info/top_level.txt
zerotk/lib/__init__.py
zerotk/lib/gitignored.py
zerotk/lib/path.py
zerotk/lib/text.py
zerotk/lib/url.py
zerotk/lib/version.py
zerotk/lib/yaml.py
zerotk/lib/_tests/test_gitignored.py
zerotk/lib/_tests/test_text.py
zerotk/lib/_tests/test_url.py
zerotk/lib/_tests/test_yaml.py
zerotk/lib/_tests/test_gitignored/test_00/.gitignore
zerotk/lib/_tests/test_gitignored/test_00/git-root.txt
zerotk/lib/_tests/test_gitignored/test_00/placed-holder.txt
zerotk/lib/_tests/test_gitignored/test_00/included/alpha.txt