Metadata-Version: 1.1
Name: zerotk.lib
Version: 1.3.1
Summary: Collection of basic Python utilities.
Home-page: https://github.com/zerotk/zerotk.lib
Author: Alexandre Andrade
Author-email: kaniabi@gmail.com
License: MIT license
Platform: UNKNOWN
Classifier: Development Status :: 2 - Pre-Alpha
Classifier: Intended Audience :: Developers
Classifier: License :: OSI Approved :: MIT License
Classifier: Natural Language :: English
Classifier: Programming Language :: Python :: 3
Classifier: Programming Language :: Python :: 3.6
